python_iugu/__init__.py
python_iugu/enuns.py
python_iugu/expcetion.py
python_iugu/test.py
python_iugu/utils.py
python_iugu/version.py
python_iugu/client/__init__.py
python_iugu/client/client.py
python_iugu/client/iclient.py
python_iugu/model/__init__.py
python_iugu/model/custom_variable_model.py
python_iugu/model/customer_model.py
python_iugu/model/invoice_model.py
python_iugu/model/item_model.py
python_iugu/model/log_model.py
python_iugu/model/payment_method_model.py
python_iugu/model/plan_model.py
python_iugu/model/subscription_model.py
python_iugu/request/__init__.py
python_iugu/request/customer_request.py
python_iugu/request/invoice_request.py
python_iugu/request/plan_request.py
python_iugu/request/subscription_request.py
python_iugu/request/utils_request.py
python_iugu/service/__init__.py
python_iugu/service/base_service.py
python_iugu/service/customer_service.py
python_iugu/service/invoice_service.py
python_iugu/service/plan_service.py
python_iugu/service/subscription_service.py
python_iugu-0.4.0.dist-info/LICENSE
python_iugu-0.4.0.dist-info/METADATA
python_iugu-0.4.0.dist-info/WHEEL
python_iugu-0.4.0.dist-info/top_level.txt
python_iugu-0.4.0.dist-info/RECORD
