Metadata-Version: 2.1
Name: python-iugu
Version: 0.4.0
Summary: This provides Python REST APIs to create, process and manage payments on IUGU.
Home-page: UNKNOWN
Author: Guilherme Silva
Author-email: guilherme.1995lemes@gmail.com
License: MIT
Keywords: iugu,rest,payment
Platform: UNKNOWN
Classifier: Development Status :: 3 - Alpha
Classifier: Intended Audience :: Developers
Classifier: Natural Language :: English
Classifier: Operating System :: OS Independent
Classifier: Topic :: Software Development :: Build Tools
Classifier: License :: OSI Approved :: MIT License
Classifier: Programming Language :: Python :: 3.7
Classifier: Programming Language :: Python :: 3.8
Classifier: Programming Language :: Python :: 3.9
Requires-Dist: aiohttp (~=3.7.3)
Requires-Dist: deserialize (~=1.8.0)
Requires-Dist: setuptools (~=51.1.1)
